pyflowlauncher/__init__.py
pyflowlauncher/api.py
pyflowlauncher/event.py
pyflowlauncher/icons.py
pyflowlauncher/jsonrpc.py
pyflowlauncher/manifest.py
pyflowlauncher/method.py
pyflowlauncher/plugin.py
pyflowlauncher/py.typed
pyflowlauncher/result.py
pyflowlauncher/settings.py
pyflowlauncher/shared.py
pyflowlauncher/string_matcher.py
pyflowlauncher/utils.py
pyflowlauncher-0.9.2.dist-info/LICENSE
pyflowlauncher-0.9.2.dist-info/METADATA
pyflowlauncher-0.9.2.dist-info/WHEEL
pyflowlauncher-0.9.2.dist-info/top_level.txt
pyflowlauncher-0.9.2.dist-info/RECORD
