Metadata-Version: 2.1
Name: pyflowlauncher
Version: 0.9.2
Summary: Python library to help build Flow Launcher plugins.
Author-email: William McAllister <dev.garulf@gmail.com>
License: MIT
Classifier: License :: OSI Approved :: MIT License
Classifier: Programming Language :: Python :: 3.8
Classifier: Programming Language :: Python :: 3.9
Classifier: Programming Language :: Python :: 3.10
Classifier: Programming Language :: Python :: 3.11
Classifier: Programming Language :: Python :: 3.12
Classifier: Typing :: Typed
Requires-Python: >=3.8
Provides-Extra: all
License-File: LICENSE
